damnklr/__init__.py
damnklr/damnklr.py
damnklr-0.1.dist-info/METADATA
damnklr-0.1.dist-info/WHEEL
damnklr-0.1.dist-info/top_level.txt
damnklr-0.1.dist-info/RECORD
